[
  {
    "clubName": "Cooking & Foodie Club",
    "description": "A club for culinary enthusiasts to share recipes, cooking tips, and organize tasting events.",
    "category": "Food & Cooking",
    "location": "Dhaka",
    "bannerImage": "https://www.verywellhealth.com/thmb/ZQWEa_Sb-bMLWLcR7-4KIbEvWVo=/1500x0/filters:no_upscale():max_bytes(150000):strip_icc()/GettyImages-1204545515-d186393c71414abbbed7b695f20c43bd.jpg",
    "membershipFee": 10,
    "status": "approved",
    "managerEmail": "manager1@example.com",
    "createdAt": "2025-12-07T22:00:00Z",
    "updatedAt": "2025-12-07T22:00:00Z"
  },
  {
    "clubName": "Music Jam Club",
    "description": "Join fellow musicians to jam, perform, and explore different music genres together.",
    "category": "Music",
    "location": "Dhaka",
    "bannerImage": "https://img.freepik.com/premium-psd/closeup-drum-set-street-performance_538547-9398.jpg?semt=ais_hybrid&w=740&q=80",
    "membershipFee": 5,
    "status": "approved",
    "managerEmail": "manager2@example.com",
    "createdAt": "2025-12-07T22:05:00Z",
    "updatedAt": "2025-12-07T22:05:00Z"
  },
  {
    "clubName": "Travel & Adventure Group",
    "description": "Organize trips, hiking adventures, and travel experiences with fellow explorers.",
    "category": "Travel",
    "location": "Chittagong",
    "bannerImage": "https://plus.unsplash.com/premium_photo-1667516408599-67d72068eaa9?fm=jpg&q=60&w=3000&ixlib=rb-4.1.0&ixid=M3wxMjA3fDB8MHxzZWFyY2h8MXx8YWR2ZW50dXJlJTIwdHJhdmVsfGVufDB8fDB8fHww",
    "membershipFee": 0,
    "status": "approved",
    "managerEmail": "manager3@example.com",
    "createdAt": "2025-12-07T22:10:00Z",
    "updatedAt": "2025-12-07T22:10:00Z"
  },
  {
    "clubName": "Board Games & Card Games Club",
    "description": "Play and learn new board games and card games while meeting new friends.",
    "category": "Games",
    "location": "Dhaka",
    "bannerImage": "https://www.gse.harvard.edu/sites/default/files/styles/16x9__focal_point_scale_and_crop__md/public/content-images/1500x750-student-game-club.jpg?h=16a6ccf5&itok=qpPhIvKj",
    "membershipFee": 0,
    "status": "approved",
    "managerEmail": "manager4@example.com",
    "createdAt": "2025-12-07T22:15:00Z",
    "updatedAt": "2025-12-07T22:15:00Z"
  },
  {
    "clubName": "Fitness & Wellness Club",
    "description": "Stay active and healthy with group workouts, fitness challenges, and wellness workshops.",
    "category": "Fitness",
    "location": "Sylhet",
    "bannerImage": "https://crescentclubandspa.com/wp-content/uploads/2020/10/hero-wellness.png",
    "membershipFee": 15,
    "status": "approved",
    "managerEmail": "manager5@example.com",
    "createdAt": "2025-12-07T22:20:00Z",
    "updatedAt": "2025-12-07T22:20:00Z"
  },
  {
    "clubName": "Coffee Lovers Meetup Group",
    "description": "Meet other coffee enthusiasts, explore cafés, and share your love for coffee.",
    "category": "Food & Beverage",
    "location": "Dhaka",
    "bannerImage": "https://img.freepik.com/free-photo/elderly-women-drinking-coffee-gathering_23-2149230380.jpg?semt=ais_hybrid&w=740&q=80",
    "membershipFee": 0,
    "status": "approved",
    "managerEmail": "manager6@example.com",
    "createdAt": "2025-12-07T22:25:00Z",
    "updatedAt": "2025-12-07T22:25:00Z"
  },
  {
    "clubName": "Yoga & Mindfulness Circle",
    "description": "Practice yoga and mindfulness to enhance physical and mental well-being.",
    "category": "Fitness",
    "location": "Chittagong",
    "bannerImage": "https://www.opencircleyoga.org/storage/app/uploads/public/67d/fd1/5ca/67dfd15cabd2a635947259.jpeg",
    "membershipFee": 10,
    "status": "approved",
    "managerEmail": "manager7@example.com",
    "createdAt": "2025-12-07T22:30:00Z",
    "updatedAt": "2025-12-07T22:30:00Z"
  },
  {
    "clubName": "Art & Craft Creativity Club",
    "description": "Explore your artistic side with painting, crafting, and creative workshops.",
    "category": "Art",
    "location": "Dhaka",
    "bannerImage": "https://images.unsplash.com/photo-1513364776144-60967b0f800f",
    "membershipFee": 5,
    "status": "approved",
    "managerEmail": "manager8@example.com",
    "createdAt": "2025-12-07T22:35:00Z",
    "updatedAt": "2025-12-07T22:35:00Z"
  },
  {
    "clubName": "Movie & Film Discussion Club",
    "description": "Watch movies together and discuss plots, directors, and cinematic techniques.",
    "category": "Film",
    "location": "Khulna",
    "bannerImage": "https://qantara.de/sites/default/files/import/2016-11/71055-cinema_club_jesuit_teaser.jpg",
    "membershipFee": 0,
    "status": "approved",
    "managerEmail": "manager9@example.com",
    "createdAt": "2025-12-07T22:40:00Z",
    "updatedAt": "2025-12-07T22:40:00Z"
  },
  {
    "clubName": "Language Exchange Club",
    "description": "Practice new languages and learn about cultures with fellow enthusiasts.",
    "category": "Education",
    "location": "Dhaka",
    "bannerImage": "https://images.unsplash.com/photo-1503676260728-1c00da094a0b",
    "membershipFee": 0,
    "status": "approved",
    "managerEmail": "manager10@example.com",
    "createdAt": "2025-12-07T22:45:00Z",
    "updatedAt": "2025-12-07T22:45:00Z"
  },
  {
    "clubName": "Coding & Programming Club",
    "description": "Collaborate on coding projects, learn new programming skills, and hackathons.",
    "category": "Tech",
    "location": "Dhaka",
    "bannerImage": "https://southleedslife.com/wp-content/uploads/Coding-Club-1.jpg",
    "membershipFee": 5,
    "status": "approved",
    "managerEmail": "manager11@example.com",
    "createdAt": "2025-12-07T22:50:00Z",
    "updatedAt": "2025-12-07T22:50:00Z"
  },
  {
    "clubName": "Gardening & Nature Club",
    "description": "Share gardening tips, organize nature walks, and grow plants together.",
    "category": "Nature",
    "location": "Sylhet",
    "bannerImage": "https://img.freepik.com/free-photo/overhead-view-smiling-female-holding-grown-fresh-strawberry-plant-garden_23-2148165284.jpg?semt=ais_hybrid&w=740&q=80",
    "membershipFee": 0,
    "status": "approved",
    "managerEmail": "manager12@example.com",
    "createdAt": "2025-12-07T22:55:00Z",
    "updatedAt": "2025-12-07T22:55:00Z"
  },
  {
    "clubName": "Dance & Zumba Group",
    "description": "Learn dance routines, enjoy Zumba sessions, and stay fit with music.",
    "category": "Fitness",
    "location": "Dhaka",
    "bannerImage": "https://www.growinnsteps.com/wp-content/uploads/2022/06/dancer-zumba-fitness-training-dance-studio-scaled-1.jpg",
    "membershipFee": 10,
    "status": "approved",
    "managerEmail": "manager13@example.com",
    "createdAt": "2025-12-07T23:00:00Z",
    "updatedAt": "2025-12-07T23:00:00Z"
  },
  {
    "clubName": "Chess & Strategy Games Club",
    "description": "Challenge others in chess and strategy games, participate in tournaments.",
    "category": "Games",
    "location": "Chittagong",
    "bannerImage": "https://media.licdn.com/dms/image/v2/D4E12AQE-XhAB38ylvQ/article-cover_image-shrink_720_1280/article-cover_image-shrink_720_1280/0/1679480460492?e=2147483647&v=beta&t=MhxxPkH-RYvBRk1g9gAd9W5kX18uHvP5s3__C1lvqoI",
    "membershipFee": 0,
    "status": "approved",
    "managerEmail": "manager14@example.com",
    "createdAt": "2025-12-07T23:05:00Z",
    "updatedAt": "2025-12-07T23:05:00Z"
  },
  {
    "clubName": "Cycling & Outdoor Activity Group",
    "description": "Organize cycling trips, outdoor sports, and adventure activities.",
    "category": "Sports",
    "location": "Dhaka",
    "bannerImage": "https://styrkr.com/cdn/shop/articles/cycling_benefits_styrkr_1200x1200.jpg?v=1676894305",
    "membershipFee": 0,
    "status": "approved",
    "managerEmail": "manager15@example.com",
    "createdAt": "2025-12-07T23:10:00Z",
    "updatedAt": "2025-12-07T23:10:00Z"
  },
  {
    "clubName": "Drama & Acting Club",
    "description": "Explore acting skills, organize plays, and participate in drama workshops.",
    "category": "Art",
    "location": "Dhaka",
    "bannerImage": "https://www.cssd.ac.uk/sites/default/files/styles/twitter_card_image/public/2021-02/CSSD_BA-Acting-CDT_Tomorrow-I%27ll-be-Twenty_P.jpg?h=b0bbe8d3&itok=9tSfMB9R",
    "membershipFee": 5,
    "status": "approved",
    "managerEmail": "manager16@example.com",
    "createdAt": "2025-12-07T23:15:00Z",
    "updatedAt": "2025-12-07T23:15:00Z"
  },
  {
    "clubName": "Volunteering & Community Service Group",
    "description": "Participate in community service projects and volunteer for social causes.",
    "category": "Community",
    "location": "Khulna",
    "bannerImage": "https://ivhq.imgix.net/images/pages/volunteer-activity-ideas/volunteer-acitivty-ideascommunity-clean-up.png?w=850&fit=max&auto=compress%2Cformat",
    "membershipFee": 0,
    "status": "approved",
    "managerEmail": "manager17@example.com",
    "createdAt": "2025-12-07T23:20:00Z",
    "updatedAt": "2025-12-07T23:20:00Z"
  },
  {
    "clubName": "Cultural Exchange & Diversity Club",
    "description": "Promote cultural understanding through events, workshops, and meetups.",
    "category": "Culture",
    "location": "Dhaka",
    "bannerImage": "https://img.freepik.com/premium-vector/show-colorful-diverse-gathering-people-from-different-cultures-celebration-unity-cultural-exchange_372046-50391.jpg",
    "membershipFee": 5,
    "status": "approved",
    "managerEmail": "manager18@example.com",
    "createdAt": "2025-12-07T23:25:00Z",
    "updatedAt": "2025-12-07T23:25:00Z"
  },
  {
    "clubName": "Entrepreneurship & Start-Up Club",
    "description": "Support budding entrepreneurs with workshops, networking, and mentorship.",
    "category": "Business",
    "location": "Dhaka",
    "bannerImage": "https://media.licdn.com/dms/image/v2/C4D1BAQFkdL7t3GjZxQ/company-background_10000/company-background_10000/0/1613644736667/the_startup_club_world_cover?e=2147483647&v=beta&t=Bp1CSCpLK0MhfZGoeSVMMuhPx2PVJy0HA_bAlJwy_2g",
    "membershipFee": 15,
    "status": "approved",
    "managerEmail": "manager19@example.com",
    "createdAt": "2025-12-07T23:30:00Z",
    "updatedAt": "2025-12-07T23:30:00Z"
  },
  {
    "clubName": "Meditation & Spiritual Growth Group",
    "description": "Practice meditation and explore spiritual growth in a supportive community.",
    "category": "Wellness",
    "location": "Sylhet",
    "bannerImage": "https://img.freepik.com/free-vector/open-air-yoga-class-concept_52683-45580.jpg?semt=ais_hybrid&w=740&q=80",
    "membershipFee": 0,
    "status": "approved",
    "managerEmail": "manager20@example.com",
    "createdAt": "2025-12-07T23:35:00Z",
    "updatedAt": "2025-12-07T23:35:00Z"
  }
]
